Metadata-Version: 2.4
Name: bytedocs-django
Version: 0.1.2
Summary: Alternative to Swagger with better design, auto-detection, and AI integration
Home-page: https://github.com/bytedocs/bytedocs-django
Author: ByteDocs Team
Author-email: bytedocs.dev@gmail.com
Project-URL: Bug Reports, https://github.com/bytedocs/bytedocs-django/issues
Project-URL: Source, https://github.com/bytedocs/bytedocs-django
Project-URL: Documentation, https://docs.bytedocs.com
Keywords: django api documentation swagger openapi rest-framework bytedocs
Classifier: Development Status :: 4 - Beta
Classifier: Intended Audience :: Developers
Classifier: License :: OSI Approved :: MIT License
Classifier: Programming Language :: Python :: 3
Classifier: Programming Language :: Python :: 3.8
Classifier: Programming Language :: Python :: 3.9
Classifier: Programming Language :: Python :: 3.10
Classifier: Programming Language :: Python :: 3.11
Classifier: Programming Language :: Python :: 3.12
Classifier: Framework :: Django
Classifier: Framework :: Django :: 3.2
Classifier: Framework :: Django :: 4.0
Classifier: Framework :: Django :: 4.1
Classifier: Framework :: Django :: 4.2
Classifier: Framework :: Django :: 5.0
Classifier: Topic :: Software Development :: Documentation
Classifier: Topic :: Software Development :: Libraries :: Python Modules
Requires-Python: >=3.8
License-File: LICENSE
Requires-Dist: Django>=3.2
Requires-Dist: pyyaml>=6.0
Requires-Dist: python-dotenv>=1.0.0
Provides-Extra: ai
Requires-Dist: openai>=2.0.0; extra == "ai"
Requires-Dist: google-generativeai>=0.8.0; extra == "ai"
Requires-Dist: anthropic>=0.70.0; extra == "ai"
Provides-Extra: drf
Requires-Dist: djangorestframework>=3.14.0; extra == "drf"
Provides-Extra: dev
Requires-Dist: pytest>=7.0.0; extra == "dev"
Requires-Dist: pytest-django>=4.5.0; extra == "dev"
Requires-Dist: black>=23.0.0; extra == "dev"
Requires-Dist: flake8>=6.0.0; extra == "dev"
Dynamic: author
Dynamic: author-email
Dynamic: classifier
Dynamic: description
Dynamic: description-content-type
Dynamic: home-page
Dynamic: keywords
Dynamic: license-file
Dynamic: project-url
Dynamic: provides-extra
Dynamic: requires-dist
Dynamic: requires-python
Dynamic: summary
